llama_index/readers/datasets/__init__.py
llama_index/readers/datasets/base.py
llama_index_readers_datasets-0.1.0.dist-info/METADATA
llama_index_readers_datasets-0.1.0.dist-info/WHEEL
llama_index_readers_datasets-0.1.0.dist-info/licenses/LICENSE
llama_index_readers_datasets-0.1.0.dist-info/RECORD
