Metadata-Version: 2.4
Name: llama-index-readers-datasets
Version: 0.1.0
Summary: llama-index readers HuggingFace Datasets integration
Author-email: Florian Bacho <f.bacho@outlook.fr>
Maintainer: Florian-BACHO
License-Expression: MIT
License-File: LICENSE
Keywords: datasets,huggingface
Requires-Python: <4.0,>=3.9
Requires-Dist: datasets>=4.4.2
Requires-Dist: llama-index-core<0.15,>=0.13.0
